audio_title_tag.py
audio_title_tag-1.3.dist-info/METADATA
audio_title_tag-1.3.dist-info/WHEEL
audio_title_tag-1.3.dist-info/RECORD
