Metadata-Version: 2.1
Name: audio_title_tag
Version: 1.3
Summary: 批量设置文件夹内的mp3、flac音频文件元数据标签的标题为当前文件名称
Home-page: https://github.com/myally/audio_title_tag
License: MIT
Author: BlackWhite
Author-email: jierong8215@gmail.com
Requires-Python: >=3.6
Classifier: License :: OSI Approved :: MIT License
Classifier: Programming Language :: Python :: 3
Classifier: Programming Language :: Python :: 3.6
Classifier: Programming Language :: Python :: 3.7
Classifier: Programming Language :: Python :: 3.8
Classifier: Programming Language :: Python :: 3.9
Classifier: Programming Language :: Python :: 3.10
Classifier: Programming Language :: Python :: 3.11
Requires-Dist: eyed3 (==0.9.7)
Requires-Dist: mutagen (==1.46.0)
Project-URL: Repository, https://github.com/myally/audio_title_tag
